.gitignore
MANIFEST.in
README.rst
bootstrap.py
buildout.cfg
collective.categories-configure.zcml
setup.py
collective/__init__.py
collective.categories.egg-info/PKG-INFO
collective.categories.egg-info/SOURCES.txt
collective.categories.egg-info/dependency_links.txt
collective.categories.egg-info/entry_points.txt
collective.categories.egg-info/namespace_packages.txt
collective.categories.egg-info/not-zip-safe
collective.categories.egg-info/requires.txt
collective.categories.egg-info/top_level.txt
collective/categories/__init__.py
collective/categories/backend.py
collective/categories/backend_atvm.py
collective/categories/backend_linguakeyword.py
collective/categories/configure.zcml
collective/categories/extender.py
collective/categories/keywords.pt
collective/categories/layer.py
collective/categories/rebuild_i18n.sh
collective/categories/testing.py
collective/categories/upgrades.py
collective/categories/upgrades.zcml
collective/categories/viewlet.py
collective/categories/vocabulary.py
collective/categories/locales/collective.categories.pot
collective/categories/locales/en/LC_MESSAGES/collective.categories.po
collective/categories/locales/fr/LC_MESSAGES/collective.categories.po
collective/categories/profiles/default/browserlayer.xml
collective/categories/profiles/default/catalog.xml
collective/categories/profiles/default/collective.categories.txt
collective/categories/profiles/default/metadata.xml
collective/categories/profiles/default/portal_atct.xml
collective/categories/profiles/default/registry.xml
collective/categories/profiles/default/skins.xml
collective/categories/skins/collective_categories/collectKeywords.py
collective/categories/tests/__init__.py
collective/categories/tests/base.py
collective/categories/tests/test_setup.py
docs/HISTORY.txt